{
  "title": "Rubin 拆解投资观察池日报 2026-05-25",
  "slug": "rubin-daily",
  "date": "2026-05-25",
  "author": "Kerwin",
  "category": "AI Research",
  "summary": "基于 Morgan Stanley Rubin/VR200 相对 Blackwell/GB300 的 BOM 拆解，追踪 Memory、PCB、MLCC、Networking、ABF、Power/Cooling 观察池每日涨跌幅（1D / MTD / YTD）。",
  "tags": [
    "Rubin",
    "NVIDIA",
    "AI Infrastructure",
    "日报",
    "PCB",
    "Memory",
    "MLCC",
    "Investment"
  ],
  "source": "Kerwin Team x OpenClaw Abba",
  "published": true,
  "published_at": "2026-05-25T18:10:54.544183+08:00",
  "homepage_approved": false
}